<Item class="Model" referent="RBX3D20D490809549A692E7447DE0AB1FD7">
			<Properties>
				<BinaryString name="AttributesSerialize" />
				<SecurityCapabilities name="Capabilities">0</SecurityCapabilities>
				<bool name="DefinesCapabilities">false</bool>
				<token name="LevelOfDetail">0</token>
				<CoordinateFrame name="ModelMeshCFrame">
					<X>0</X>
					<Y>0</Y>
					<Z>0</Z>
					<R00>1</R00>
					<R01>0</R01>
					<R02>0</R02>
					<R10>0</R10>
					<R11>1</R11>
					<R12>0</R12>
					<R20>0</R20>
					<R21>0</R21>
					<R22>1</R22>
				</CoordinateFrame>
				<SharedString name="ModelMeshData">yuZpQdnvvUBOTYh1jqZ2cA==</SharedString>
				<Vector3 name="ModelMeshSize">
					<X>0</X>
					<Y>0</Y>
					<Z>0</Z>
				</Vector3>
				<token name="ModelStreamingMode">0</token>
				<string name="Name">128160832</string>
				<bool name="NeedsPivotMigration">false</bool>
				<Ref name="PrimaryPart">null</Ref>
				<float name="ScaleFactor">1</float>
				<int64 name="SourceAssetId">-1</int64>
				<BinaryString name="Tags" />
				<OptionalCoordinateFrame name="WorldPivotData" />
			</Properties>
			<Item class="Tool" referent="RBXABA8682614FF4B64AECD873BB9088DC0">
				<Properties>
					<BinaryString name="AttributesSerialize" />
					<bool name="CanBeDropped">true</bool>
					<SecurityCapabilities name="Capabilities">0</SecurityCapabilities>
					<bool name="DefinesCapabilities">false</bool>
					<bool name="Enabled">true</bool>
					<CoordinateFrame name="Grip">
						<X>0</X>
						<Y>-0.349999994</Y>
						<Z>0.100000001</Z>
						<R00>0.621609986</R00>
						<R01>0</R01>
						<R02>-0.783326924</R02>
						<R10>-0.305041879</R10>
						<R11>0.921060979</R11>
						<R12>-0.242066324</R12>
						<R20>0.721491873</R20>
						<R21>0.389418334</R21>
						<R22>0.5725407</R22>
					</CoordinateFrame>
					<token name="LevelOfDetail">0</token>
					<bool name="ManualActivationOnly">false</bool>
					<CoordinateFrame name="ModelMeshCFrame">
						<X>0</X>
						<Y>0</Y>
						<Z>0</Z>
						<R00>1</R00>
						<R01>0</R01>
						<R02>0</R02>
						<R10>0</R10>
						<R11>1</R11>
						<R12>0</R12>
						<R20>0</R20>
						<R21>0</R21>
						<R22>1</R22>
					</CoordinateFrame>
					<SharedString name="ModelMeshData">yuZpQdnvvUBOTYh1jqZ2cA==</SharedString>
					<Vector3 name="ModelMeshSize">
						<X>0</X>
						<Y>0</Y>
						<Z>0</Z>
					</Vector3>
					<token name="ModelStreamingMode">0</token>
					<string name="Name">Whistle</string>
					<bool name="NeedsPivotMigration">false</bool>
					<Ref name="PrimaryPart">null</Ref>
					<bool name="RequiresHandle">true</bool>
					<float name="ScaleFactor">1</float>
					<int64 name="SourceAssetId">-1</int64>
					<BinaryString name="Tags" />
					<Content name="TextureId"><url>http://www.roblox.com/asset/?id=128121687</url></Content>
					<string name="ToolTip">Time for dodgeball!</string>
					<OptionalCoordinateFrame name="WorldPivotData">
						<CFrame>
							<X>-65.3120041</X>
							<Y>7.39000034</Y>
							<Z>-44.7130013</Z>
							<R00>-0.864901245</R00>
							<R01>-0.135058314</R01>
							<R02>0.483430207</R02>
							<R10>0.0685266331</R10>
							<R11>0.922330379</R11>
							<R12>0.380277365</R12>
							<R20>-0.497242182</R20>
							<R21>0.362030089</R21>
							<R22>-0.788469017</R22>
						</CFrame>
					</OptionalCoordinateFrame>
				</Properties>
				<Item class="Part" referent="RBXA54AAF6B13FD499D831E579161E8EF69">
					<Properties>
						<bool name="Anchored">false</bool>
						<BinaryString name="AttributesSerialize" />
						<bool name="AudioCanCollide">true</bool>
						<float name="BackParamA">-0.5</float>
						<float name="BackParamB">0.5</float>
						<token name="BackSurface">0</token>
						<token name="BackSurfaceInput">0</token>
						<float name="BottomParamA">-0.5</float>
						<float name="BottomParamB">0.5</float>
						<token name="BottomSurface">4</token>
						<token name="BottomSurfaceInput">0</token>
						<CoordinateFrame name="CFrame">
							<X>-65.3120041</X>
							<Y>7.39000034</Y>
							<Z>-44.7130013</Z>
							<R00>-0.864901245</R00>
							<R01>-0.135058314</R01>
							<R02>0.483430207</R02>
							<R10>0.0685266331</R10>
							<R11>0.922330379</R11>
							<R12>0.380277365</R12>
							<R20>-0.497242182</R20>
							<R21>0.362030089</R21>
							<R22>-0.788469017</R22>
						</CoordinateFrame>
						<bool name="CanCollide">true</bool>
						<bool name="CanQuery">true</bool>
						<bool name="CanTouch">true</bool>
						<SecurityCapabilities name="Capabilities">0</SecurityCapabilities>
						<bool name="CastShadow">true</bool>
						<string name="CollisionGroup">Default</string>
						<int name="CollisionGroupId">0</int>
						<Color3uint8 name="Color3uint8">4288914085</Color3uint8>
						<PhysicalProperties name="CustomPhysicalProperties">
							<CustomPhysics>false</CustomPhysics>
						</PhysicalProperties>
						<bool name="DefinesCapabilities">false</bool>
						<bool name="EnableFluidForces">true</bool>
						<float name="FrontParamA">-0.5</float>
						<float name="FrontParamB">0.5</float>
						<token name="FrontSurface">0</token>
						<token name="FrontSurfaceInput">0</token>
						<float name="LeftParamA">-0.5</float>
						<float name="LeftParamB">0.5</float>
						<token name="LeftSurface">0</token>
						<token name="LeftSurfaceInput">0</token>
						<bool name="Locked">true</bool>
						<bool name="Massless">false</bool>
						<token name="Material">256</token>
						<string name="MaterialVariantSerialized" />
						<string name="Name">Handle</string>
						<CoordinateFrame name="PivotOffset">
							<X>0</X>
							<Y>0</Y>
							<Z>0</Z>
							<R00>1</R00>
							<R01>0</R01>
							<R02>0</R02>
							<R10>0</R10>
							<R11>1</R11>
							<R12>0</R12>
							<R20>0</R20>
							<R21>0</R21>
							<R22>1</R22>
						</CoordinateFrame>
						<float name="Reflectance">0.349999994</float>
						<float name="RightParamA">-0.5</float>
						<float name="RightParamB">0.5</float>
						<token name="RightSurface">0</token>
						<token name="RightSurfaceInput">0</token>
						<int name="RootPriority">0</int>
						<Vector3 name="RotVelocity">
							<X>0</X>
							<Y>0</Y>
							<Z>0</Z>
						</Vector3>
						<int64 name="SourceAssetId">-1</int64>
						<BinaryString name="Tags" />
						<float name="TopParamA">-0.5</float>
						<float name="TopParamB">0.5</float>
						<token name="TopSurface">3</token>
						<token name="TopSurfaceInput">0</token>
						<float name="Transparency">0</float>
						<Vector3 name="Velocity">
							<X>0</X>
							<Y>0</Y>
							<Z>0</Z>
						</Vector3>
						<token name="formFactorRaw">3</token>
						<token name="shape">1</token>
						<Vector3 name="size">
							<X>0.400000006</X>
							<Y>0.400000006</Y>
							<Z>0.899999976</Z>
						</Vector3>
					</Properties>
					<Item class="SpecialMesh" referent="RBXBA5B9F2622FB40DB8894B5470CBA01BC">
						<Properties>
							<BinaryString name="AttributesSerialize" />
							<SecurityCapabilities name="Capabilities">0</SecurityCapabilities>
							<bool name="DefinesCapabilities">false</bool>
							<Content name="MeshId"><url>http://www.roblox.com/asset/?id=128121591</url></Content>
							<token name="MeshType">5</token>
							<string name="Name">Mesh</string>
							<Vector3 name="Offset">
								<X>0</X>
								<Y>0</Y>
								<Z>0</Z>
							</Vector3>
							<Vector3 name="Scale">
								<X>1</X>
								<Y>1</Y>
								<Z>1</Z>
							</Vector3>
							<int64 name="SourceAssetId">-1</int64>
							<BinaryString name="Tags" />
							<Content name="TextureId"><url>http://www.roblox.com/asset/?id=128121760</url></Content>
							<Vector3 name="VertexColor">
								<X>1</X>
								<Y>1</Y>
								<Z>1</Z>
							</Vector3>
						</Properties>
					</Item>
					<Item class="Sound" referent="RBXE91BDCEF546D4B199EF1C2AA81A1828D">
						<Properties>
							<BinaryString name="AttributesSerialize" />
							<SecurityCapabilities name="Capabilities">0</SecurityCapabilities>
							<bool name="DefinesCapabilities">false</bool>
							<bool name="IsMutedForCapture">false</bool>
							<NumberRange name="LoopRegion">0 60000 </NumberRange>
							<bool name="Looped">false</bool>
							<string name="Name">Sound</string>
							<bool name="PlayOnRemove">false</bool>
							<NumberRange name="PlaybackRegion">0 60000 </NumberRange>
							<bool name="PlaybackRegionsEnabled">false</bool>
							<float name="PlaybackSpeed">1</float>
							<bool name="Playing">false</bool>
							<float name="RollOffMaxDistance">10000</float>
							<float name="RollOffMinDistance">10</float>
							<token name="RollOffMode">0</token>
							<Ref name="SoundGroup">null</Ref>
							<Content name="SoundId"><url>http://www.roblox.com/asset/?id=128123893</url></Content>
							<int64 name="SourceAssetId">-1</int64>
							<BinaryString name="Tags" />
							<double name="TimePosition">0</double>
							<float name="Volume">1</float>
						</Properties>
					</Item>
				</Item>
				<Item class="LocalScript" referent="RBX1258BA8DC5554D69BA8B71A8BCCCC21E">
					<Properties>
						<BinaryString name="AttributesSerialize" />
						<SecurityCapabilities name="Capabilities">0</SecurityCapabilities>
						<bool name="DefinesCapabilities">false</bool>
						<bool name="Disabled">false</bool>
						<Content name="LinkedSource"><null /></Content>
						<string name="Name">WhistleLocalScript</string>
						<token name="RunContext">0</token>
						<string name="ScriptGuid">{9AB4E80A-7867-4C1B-9805-A4909DE009C4}</string>
						<ProtectedString name="Source">--Made by Stickmasterluke


sp=script.Parent


local cooldown=10
local jetheight=200
local jetdistance=2000
local jetspeed=300
local talkinggrip=CFrame.new(-1.5,-.5,.65)*CFrame.Angles(-.2,3.14159,0)
local holdinggrip=CFrame.new(0,-.35,.1)*CFrame.Angles(.4,-.9,0)


local debris=game:GetService("Debris")
local check=true
local laststrike=sp:WaitForChild("LastStrike")
local dodgeballscript=sp:WaitForChild("DodgeballScript")

local function createdodgeball(pos,velocity)
	local p=Instance.new("Part")
	p.Name="Dodgeball"
	p.Material="Concrete"
	p.BrickColor=BrickColor.new(math.random()&gt;.5 and "Bright red" or "Bright blue")
	p.Elasticity=1
	p.CanCollide=true
	p.Locked=true
	p.TopSurface="Smooth"
	p.BottomSurface="Smooth"
	p.formFactor="Custom"
	p.Shape="Ball"

	local sound=Instance.new("Sound")
	sound.SoundId="http://www.roblox.com/asset/?id=112503990"
	sound.Parent=p

	local creatortag=Instance.new("ObjectValue")
	creatortag.Value=game.Players.LocalPlayer
	creatortag.Name="creator"
	creatortag.Parent=p

	local s=dodgeballscript:clone()
	s.Parent=p
	s.Disabled=false

	p.Size=Vector3.new(3,3,3)
	p.CFrame=CFrame.new(pos)
	p.Velocity=velocity
	debris:AddItem(p,3)
	p.Parent=game.Workspace
end

function onEquipped(mouse)
	equipped=true
	local plr=game.Players.LocalPlayer
	sp.Grip=holdinggrip
	if mouse~=nil and plr~=nil then
		if tick()-cooldown&lt;laststrike.Value then
			mouse.Icon="rbxasset://textures\\GunWaitCursor.png"
			wait(laststrike.Value-(tick()-cooldown))
			mouse.Icon="rbxasset://textures\\GunCursor.png"
		else
			mouse.Icon="rbxasset://textures\\GunCursor.png"
		end
		mouse.Button1Down:connect(function()
			if tick()-cooldown&gt;laststrike.Value and mouse.Target and mouse.Target~=nil and mouse.Hit then
				local location=mouse.Hit.p
				local chr=sp.Parent
				if chr and check then
					local t=chr:FindFirstChild("Torso")
					local h=chr:FindFirstChild("Humanoid")
					if t and h and h.Health&gt;0 then
						check=false
						laststrike.Value=tick()
						mouse.Icon="rbxasset://textures\\GunWaitCursor.png"
						sp.Grip=talkinggrip
						local sound=sp.Handle:FindFirstChild("Sound")
						if sound~=nil then
							sound:Play()
						end

						local tp=Instance.new("Part")
						tp.Transparency=.5
						tp.Name="Effect"
						tp.Anchored=true
						tp.CanCollide=false
						tp.Size=Vector3.new(0,0,0)
						tp.BrickColor=BrickColor.new("Really red")
						tp.CFrame=CFrame.new(location)*CFrame.Angles(math.pi/2,0,0)
						local me=Instance.new("SpecialMesh")
						me.MeshId="http://www.roblox.com/asset/?id=3270017"
						me.Scale=Vector3.new(10,10,1)
						me.Parent=tp
						debris:AddItem(tp,5)
						tp.Parent=game.Workspace
						delay(0,function()
							while tp and tp.Transparency&lt;1 do
								tp.Transparency=tp.Transparency+.025
								wait(.15)
							end
							if tp then
								tp:remove()
							end
						end)

						delay(3,function()
							for i=1,30 do
								local startpos=location+Vector3.new((math.random()-.5)*100,5+50*math.random(),(math.random()-.5)*100)
								local vec=(location+Vector3.new(0,15,0)-startpos).unit
								createdodgeball(startpos,vec*(60+math.random()*70))
								wait(.2)
							end
						end)

						wait(2)
						local sound=sp.Handle:FindFirstChild("Sound")
						if sound~=nil then
							sound:Stop()
						end
						sp.Grip=holdinggrip
						wait(cooldown-2)
						mouse.Icon="rbxasset://textures\\GunCursor.png"
						check=true
					end
				end
			end
		end)
	end
end

function onUnequipped()
	equipped=false
end

sp.Equipped:connect(onEquipped)
sp.Unequipped:connect(onUnequipped)


</ProtectedString>
						<int64 name="SourceAssetId">-1</int64>
						<BinaryString name="Tags" />
					</Properties>
				</Item>
				<Item class="NumberValue" referent="RBXD202AC478A694D6C9AB288A4180CBBD9">
					<Properties>
						<BinaryString name="AttributesSerialize" />
						<SecurityCapabilities name="Capabilities">0</SecurityCapabilities>
						<bool name="DefinesCapabilities">false</bool>
						<string name="Name">LastStrike</string>
						<int64 name="SourceAssetId">-1</int64>
						<BinaryString name="Tags" />
						<double name="Value">0</double>
					</Properties>
				</Item>
				<Item class="Script" referent="RBX33D62F60B4D140BB9AA2DA0014853275">
					<Properties>
						<BinaryString name="AttributesSerialize" />
						<SecurityCapabilities name="Capabilities">0</SecurityCapabilities>
						<bool name="DefinesCapabilities">false</bool>
						<bool name="Disabled">true</bool>
						<Content name="LinkedSource"><null /></Content>
						<string name="Name">DodgeballScript</string>
						<token name="RunContext">0</token>
						<string name="ScriptGuid">{34A49D4C-938B-4C12-8C0D-AC75E8B2B28B}</string>
						<ProtectedString name="Source">--Made by Stickmasterluke


sp=script.Parent


local damage=34
local sounddebounce=.5

local check=true
local lastsound=0
local debris=game:GetService("Debris")


sp.Touched:connect(function(hit)
	if hit and hit.Parent then
		if lastsound+sounddebounce&lt;time() and hit.CanCollide then
			lastsound=time()
			local sound=sp:FindFirstChild("Sound")
			if sound then
				sound.Volume=math.min(sp.Velocity.magnitude/40,1)
				sound.Pitch=.5+math.random()
				sound:Play()
			end
		end
		if damage&gt;0 then
			local h=hit.Parent:FindFirstChild("Humanoid")
			if h and h.Health&gt;0 then
				local targetplr=game.Players:GetPlayerFromCharacter(hit.Parent)
				local creatortag=sp:FindFirstChild("creator")
				print("Creator:",creatortag,creatortag.Value)
				print("Targetplr:",targetplr)
				if not creatortag or not creatortag.Value or not creatortag.Value.Parent==game.Players or not targetplr or targetplr~=creatortag.Value and (creatortag.Value.Neutral or targetplr.Neutral or targetplr.TeamColor~=creatortag.Value.TeamColor) then	--This was fun to write. Much better than sudoku. I hate sudoku.
					if creatortag then
						for _,v in pairs(h:GetChildren()) do
							if v.className=="creator" then
								v:remove()
							end
						end
						local newcreatortag=creatortag:clone()
						debris:AddItem(newcreatortag,3)
						newcreatortag.Parent=h
					end
					h:TakeDamage(damage*math.min(sp.Velocity.magnitude/40,1))
					damage=0
				end
			end
		end
	end
end)

wait(5)

sp:remove()






</ProtectedString>
						<int64 name="SourceAssetId">-1</int64>
						<BinaryString name="Tags" />
					</Properties>
				</Item>
				<Item class="Camera" referent="RBX26BAD76B5DD54953870C10362174D25B">
					<Properties>
						<BinaryString name="AttributesSerialize" />
						<CoordinateFrame name="CFrame">
							<X>-65.1352081</X>
							<Y>7.77825594</Y>
							<Z>-43.4285278</Z>
							<R00>0.991107404</R00>
							<R01>-0.0391272679</R01>
							<R02>0.127181873</R02>
							<R10>-3.72529074e-09</R10>
							<R11>0.955790937</R11>
							<R12>0.294047296</R12>
							<R20>-0.133064553</R20>
							<R21>-0.29143244</R21>
							<R22>0.947291374</R22>
						</CoordinateFrame>
						<Ref name="CameraSubject">null</Ref>
						<token name="CameraType">0</token>
						<SecurityCapabilities name="Capabilities">0</SecurityCapabilities>
						<bool name="DefinesCapabilities">false</bool>
						<float name="FieldOfView">70</float>
						<token name="FieldOfViewMode">0</token>
						<CoordinateFrame name="Focus">
							<X>-65.3895721</X>
							<Y>7.19016075</Y>
							<Z>-45.3231125</Z>
							<R00>1</R00>
							<R01>0</R01>
							<R02>0</R02>
							<R10>0</R10>
							<R11>1</R11>
							<R12>0</R12>
							<R20>0</R20>
							<R21>0</R21>
							<R22>1</R22>
						</CoordinateFrame>
						<bool name="HeadLocked">true</bool>
						<float name="HeadScale">1</float>
						<string name="Name">ThumbnailCamera</string>
						<int64 name="SourceAssetId">-1</int64>
						<BinaryString name="Tags" />
						<bool name="VRTiltAndRollEnabled">false</bool>
					</Properties>
				</Item>
			</Item>
		</Item>
		