<Item class="Model" referent="RBX8ADD8613031B4FB59E056E4A09C8F3D3">
			<Properties>
				<BinaryString name="AttributesSerialize" />
				<SecurityCapabilities name="Capabilities">0</SecurityCapabilities>
				<bool name="DefinesCapabilities">false</bool>
				<token name="LevelOfDetail">0</token>
				<CoordinateFrame name="ModelMeshCFrame">
					<X>0</X>
					<Y>0</Y>
					<Z>0</Z>
					<R00>1</R00>
					<R01>0</R01>
					<R02>0</R02>
					<R10>0</R10>
					<R11>1</R11>
					<R12>0</R12>
					<R20>0</R20>
					<R21>0</R21>
					<R22>1</R22>
				</CoordinateFrame>
				<SharedString name="ModelMeshData">yuZpQdnvvUBOTYh1jqZ2cA==</SharedString>
				<Vector3 name="ModelMeshSize">
					<X>0</X>
					<Y>0</Y>
					<Z>0</Z>
				</Vector3>
				<token name="ModelStreamingMode">0</token>
				<string name="Name">2470977704</string>
				<bool name="NeedsPivotMigration">false</bool>
				<Ref name="PrimaryPart">null</Ref>
				<float name="ScaleFactor">1</float>
				<int64 name="SourceAssetId">-1</int64>
				<BinaryString name="Tags" />
				<OptionalCoordinateFrame name="WorldPivotData" />
			</Properties>
			<Item class="Tool" referent="RBX758D5CC0CFA1478BA13F9E3A677D56AE">
				<Properties>
					<BinaryString name="AttributesSerialize" />
					<bool name="CanBeDropped">true</bool>
					<SecurityCapabilities name="Capabilities">0</SecurityCapabilities>
					<bool name="DefinesCapabilities">false</bool>
					<bool name="Enabled">true</bool>
					<CoordinateFrame name="Grip">
						<X>0</X>
						<Y>-0.600000024</Y>
						<Z>1</Z>
						<R00>1</R00>
						<R01>0</R01>
						<R02>0</R02>
						<R10>0</R10>
						<R11>1</R11>
						<R12>0</R12>
						<R20>0</R20>
						<R21>0</R21>
						<R22>1</R22>
					</CoordinateFrame>
					<token name="LevelOfDetail">0</token>
					<bool name="ManualActivationOnly">false</bool>
					<CoordinateFrame name="ModelMeshCFrame">
						<X>0</X>
						<Y>0</Y>
						<Z>0</Z>
						<R00>1</R00>
						<R01>0</R01>
						<R02>0</R02>
						<R10>0</R10>
						<R11>1</R11>
						<R12>0</R12>
						<R20>0</R20>
						<R21>0</R21>
						<R22>1</R22>
					</CoordinateFrame>
					<SharedString name="ModelMeshData">yuZpQdnvvUBOTYh1jqZ2cA==</SharedString>
					<Vector3 name="ModelMeshSize">
						<X>0</X>
						<Y>0</Y>
						<Z>0</Z>
					</Vector3>
					<token name="ModelStreamingMode">0</token>
					<string name="Name">GraveGrappler</string>
					<bool name="NeedsPivotMigration">false</bool>
					<Ref name="PrimaryPart">null</Ref>
					<bool name="RequiresHandle">true</bool>
					<float name="ScaleFactor">1</float>
					<int64 name="SourceAssetId">-1</int64>
					<BinaryString name="Tags" />
					<Content name="TextureId"><url>rbxassetid://2463973357</url></Content>
					<string name="ToolTip" />
					<OptionalCoordinateFrame name="WorldPivotData">
						<CFrame>
							<X>0.0552560017</X>
							<Y>0.506505013</Y>
							<Z>-0.0629080012</Z>
							<R00>-0.995325446</R00>
							<R01>-0.0464929342</R01>
							<R02>-0.0846504346</R02>
							<R10>2.77747958e-09</R10>
							<R11>0.876499057</R11>
							<R12>-0.48140347</R12>
							<R20>0.0965778902</R20>
							<R21>-0.479153067</R21>
							<R22>-0.872401893</R22>
						</CFrame>
					</OptionalCoordinateFrame>
				</Properties>
				<Item class="Part" referent="RBXB9306AA1A37A4C56B5A8964AE7B79CE3">
					<Properties>
						<bool name="Anchored">false</bool>
						<BinaryString name="AttributesSerialize" />
						<bool name="AudioCanCollide">true</bool>
						<float name="BackParamA">-0.5</float>
						<float name="BackParamB">0.5</float>
						<token name="BackSurface">0</token>
						<token name="BackSurfaceInput">0</token>
						<float name="BottomParamA">-0.5</float>
						<float name="BottomParamB">0.5</float>
						<token name="BottomSurface">0</token>
						<token name="BottomSurfaceInput">0</token>
						<CoordinateFrame name="CFrame">
							<X>0.0552560017</X>
							<Y>0.506505013</Y>
							<Z>-0.0629080012</Z>
							<R00>-0.995325446</R00>
							<R01>-0.0464929342</R01>
							<R02>-0.0846504346</R02>
							<R10>2.77747958e-09</R10>
							<R11>0.876499057</R11>
							<R12>-0.48140347</R12>
							<R20>0.0965778902</R20>
							<R21>-0.479153067</R21>
							<R22>-0.872401893</R22>
						</CoordinateFrame>
						<bool name="CanCollide">false</bool>
						<bool name="CanQuery">true</bool>
						<bool name="CanTouch">true</bool>
						<SecurityCapabilities name="Capabilities">0</SecurityCapabilities>
						<bool name="CastShadow">true</bool>
						<string name="CollisionGroup">Default</string>
						<int name="CollisionGroupId">0</int>
						<Color3uint8 name="Color3uint8">4279970357</Color3uint8>
						<PhysicalProperties name="CustomPhysicalProperties">
							<CustomPhysics>false</CustomPhysics>
						</PhysicalProperties>
						<bool name="DefinesCapabilities">false</bool>
						<bool name="EnableFluidForces">true</bool>
						<float name="FrontParamA">-0.5</float>
						<float name="FrontParamB">0.5</float>
						<token name="FrontSurface">0</token>
						<token name="FrontSurfaceInput">0</token>
						<float name="LeftParamA">-0.5</float>
						<float name="LeftParamB">0.5</float>
						<token name="LeftSurface">0</token>
						<token name="LeftSurfaceInput">0</token>
						<bool name="Locked">true</bool>
						<bool name="Massless">false</bool>
						<token name="Material">256</token>
						<string name="MaterialVariantSerialized" />
						<string name="Name">Handle</string>
						<CoordinateFrame name="PivotOffset">
							<X>0</X>
							<Y>0</Y>
							<Z>0</Z>
							<R00>1</R00>
							<R01>0</R01>
							<R02>0</R02>
							<R10>0</R10>
							<R11>1</R11>
							<R12>0</R12>
							<R20>0</R20>
							<R21>0</R21>
							<R22>1</R22>
						</CoordinateFrame>
						<float name="Reflectance">0</float>
						<float name="RightParamA">-0.5</float>
						<float name="RightParamB">0.5</float>
						<token name="RightSurface">0</token>
						<token name="RightSurfaceInput">0</token>
						<int name="RootPriority">0</int>
						<Vector3 name="RotVelocity">
							<X>0</X>
							<Y>0</Y>
							<Z>0</Z>
						</Vector3>
						<int64 name="SourceAssetId">-1</int64>
						<BinaryString name="Tags" />
						<float name="TopParamA">-0.5</float>
						<float name="TopParamB">0.5</float>
						<token name="TopSurface">0</token>
						<token name="TopSurfaceInput">0</token>
						<float name="Transparency">0</float>
						<Vector3 name="Velocity">
							<X>0</X>
							<Y>0</Y>
							<Z>0</Z>
						</Vector3>
						<token name="formFactorRaw">3</token>
						<token name="shape">1</token>
						<Vector3 name="size">
							<X>1</X>
							<Y>1</Y>
							<Z>2</Z>
						</Vector3>
					</Properties>
					<Item class="Sound" referent="RBX13DDA570FB5A4064B8024343B590FC94">
						<Properties>
							<BinaryString name="AttributesSerialize" />
							<SecurityCapabilities name="Capabilities">0</SecurityCapabilities>
							<bool name="DefinesCapabilities">false</bool>
							<bool name="IsMutedForCapture">false</bool>
							<NumberRange name="LoopRegion">0 60000 </NumberRange>
							<bool name="Looped">false</bool>
							<string name="Name">Connect</string>
							<bool name="PlayOnRemove">false</bool>
							<NumberRange name="PlaybackRegion">0 60000 </NumberRange>
							<bool name="PlaybackRegionsEnabled">false</bool>
							<float name="PlaybackSpeed">1</float>
							<bool name="Playing">false</bool>
							<float name="RollOffMaxDistance">10000</float>
							<float name="RollOffMinDistance">10</float>
							<token name="RollOffMode">0</token>
							<Ref name="SoundGroup">null</Ref>
							<Content name="SoundId"><url>http://www.roblox.com/asset/?id=13510737</url></Content>
							<int64 name="SourceAssetId">-1</int64>
							<BinaryString name="Tags" />
							<double name="TimePosition">0</double>
							<float name="Volume">1</float>
						</Properties>
					</Item>
					<Item class="Sound" referent="RBX2D778AD841F54991910C3FAFE23BCE06">
						<Properties>
							<BinaryString name="AttributesSerialize" />
							<SecurityCapabilities name="Capabilities">0</SecurityCapabilities>
							<bool name="DefinesCapabilities">false</bool>
							<bool name="IsMutedForCapture">false</bool>
							<NumberRange name="LoopRegion">0 60000 </NumberRange>
							<bool name="Looped">false</bool>
							<string name="Name">Fire</string>
							<bool name="PlayOnRemove">false</bool>
							<NumberRange name="PlaybackRegion">0 60000 </NumberRange>
							<bool name="PlaybackRegionsEnabled">false</bool>
							<float name="PlaybackSpeed">1</float>
							<bool name="Playing">false</bool>
							<float name="RollOffMaxDistance">10000</float>
							<float name="RollOffMinDistance">10</float>
							<token name="RollOffMode">0</token>
							<Ref name="SoundGroup">null</Ref>
							<Content name="SoundId"><url>http://www.roblox.com/asset/?id=16211041</url></Content>
							<int64 name="SourceAssetId">-1</int64>
							<BinaryString name="Tags" />
							<double name="TimePosition">0</double>
							<float name="Volume">1</float>
						</Properties>
					</Item>
					<Item class="SpecialMesh" referent="RBXD3101C52809040E698A07DAC3BB75ED8">
						<Properties>
							<BinaryString name="AttributesSerialize" />
							<SecurityCapabilities name="Capabilities">0</SecurityCapabilities>
							<bool name="DefinesCapabilities">false</bool>
							<Content name="MeshId"><url>rbxassetid://2463972118</url></Content>
							<token name="MeshType">5</token>
							<string name="Name">Mesh</string>
							<Vector3 name="Offset">
								<X>0</X>
								<Y>0</Y>
								<Z>0</Z>
							</Vector3>
							<Vector3 name="Scale">
								<X>1</X>
								<Y>1</Y>
								<Z>1</Z>
							</Vector3>
							<int64 name="SourceAssetId">-1</int64>
							<BinaryString name="Tags" />
							<Content name="TextureId"><url>rbxassetid://2463972716</url></Content>
							<Vector3 name="VertexColor">
								<X>1</X>
								<Y>1</Y>
								<Z>1</Z>
							</Vector3>
						</Properties>
					</Item>
					<Item class="Sound" referent="RBX126C72CB439A4F7DBB2BB7726FF77F7A">
						<Properties>
							<BinaryString name="AttributesSerialize" />
							<SecurityCapabilities name="Capabilities">0</SecurityCapabilities>
							<bool name="DefinesCapabilities">false</bool>
							<bool name="IsMutedForCapture">false</bool>
							<NumberRange name="LoopRegion">0 60000 </NumberRange>
							<bool name="Looped">false</bool>
							<string name="Name">Hit</string>
							<bool name="PlayOnRemove">false</bool>
							<NumberRange name="PlaybackRegion">0 60000 </NumberRange>
							<bool name="PlaybackRegionsEnabled">false</bool>
							<float name="PlaybackSpeed">1</float>
							<bool name="Playing">false</bool>
							<float name="RollOffMaxDistance">10000</float>
							<float name="RollOffMinDistance">10</float>
							<token name="RollOffMode">0</token>
							<Ref name="SoundGroup">null</Ref>
							<Content name="SoundId"><url>http://www.roblox.com/asset/?id=16211030</url></Content>
							<int64 name="SourceAssetId">-1</int64>
							<BinaryString name="Tags" />
							<double name="TimePosition">0</double>
							<float name="Volume">1</float>
						</Properties>
					</Item>
					<Item class="Attachment" referent="RBX4BD0C3D1114E43C9AB6380C797877E2E">
						<Properties>
							<BinaryString name="AttributesSerialize" />
							<CoordinateFrame name="CFrame">
								<X>-0.113774545</X>
								<Y>0.0753967315</Y>
								<Z>-0.999999821</Z>
								<R00>0</R00>
								<R01>0</R01>
								<R02>1</R02>
								<R10>0</R10>
								<R11>1</R11>
								<R12>-0</R12>
								<R20>-1</R20>
								<R21>0</R21>
								<R22>0</R22>
							</CoordinateFrame>
							<SecurityCapabilities name="Capabilities">0</SecurityCapabilities>
							<bool name="DefinesCapabilities">false</bool>
							<string name="Name">RopeAttachment</string>
							<int64 name="SourceAssetId">-1</int64>
							<BinaryString name="Tags" />
							<bool name="Visible">false</bool>
						</Properties>
					</Item>
					<Item class="Attachment" referent="RBX3DC97AF6485640F891B46A00924C7E34">
						<Properties>
							<BinaryString name="AttributesSerialize" />
							<CoordinateFrame name="CFrame">
								<X>0</X>
								<Y>-0.600000024</Y>
								<Z>1</Z>
								<R00>1</R00>
								<R01>0</R01>
								<R02>0</R02>
								<R10>0</R10>
								<R11>1</R11>
								<R12>0</R12>
								<R20>0</R20>
								<R21>0</R21>
								<R22>1</R22>
							</CoordinateFrame>
							<SecurityCapabilities name="Capabilities">0</SecurityCapabilities>
							<bool name="DefinesCapabilities">false</bool>
							<string name="Name">RightGripAttachment</string>
							<int64 name="SourceAssetId">-1</int64>
							<BinaryString name="Tags" />
							<bool name="Visible">false</bool>
						</Properties>
					</Item>
				</Item>
				<Item class="LocalScript" referent="RBXADAB9D7E7A9C4C9EAB19149BC0259C6C">
					<Properties>
						<BinaryString name="AttributesSerialize" />
						<SecurityCapabilities name="Capabilities">0</SecurityCapabilities>
						<bool name="DefinesCapabilities">false</bool>
						<bool name="Disabled">false</bool>
						<Content name="LinkedSource"><null /></Content>
						<string name="Name">LocalScript</string>
						<token name="RunContext">0</token>
						<string name="ScriptGuid">{BE594663-DED6-4A02-8167-3461EFB87F1F}</string>
						<ProtectedString name="Source">--Rescripted by Luckymaxer

Tool = script.Parent
Handle = Tool:WaitForChild("Handle")

Players = game:GetService("Players")
Debris = game:GetService("Debris")
RunService = game:GetService("RunService")
ContentProvider = game:GetService("ContentProvider")
UserInputService = game:GetService("UserInputService")

InputCheck = Instance.new("ScreenGui")
InputCheck.Name = "InputCheck"
InputFrame = Instance.new("Frame")
InputFrame.BackgroundTransparency = 1
InputFrame.Size = UDim2.new(1, 0, 1, 0)
InputFrame.Parent = InputCheck

local function Create_PrivImpl(objectType)
	if type(objectType) ~= 'string' then
		error("Argument of Create must be a string", 2)
	end
	--return the proxy function that gives us the nice Create'string'{data} syntax
	--The first function call is a function call using Lua's single-string-argument syntax
	--The second function call is using Lua's single-table-argument syntax
	--Both can be chained together for the nice effect.
	return function(dat)
		--default to nothing, to handle the no argument given case
		dat = dat or {}

		--make the object to mutate
		local obj = Instance.new(objectType)
		local parent = nil

		--stored constructor function to be called after other initialization
		local ctor = nil

		for k, v in pairs(dat) do
			--add property
			if type(k) == 'string' then
				if k == 'Parent' then
					-- Parent should always be set last, setting the Parent of a new object
					-- immediately makes performance worse for all subsequent property updates.
					parent = v
				else
					obj[k] = v
				end


			--add child
			elseif type(k) == 'number' then
				if type(v) ~= 'userdata' then
					error("Bad entry in Create body: Numeric keys must be paired with children, got a: "..type(v), 2)
				end
				v.Parent = obj


			--event connect
			elseif type(k) == 'table' and k.__eventname then
				if type(v) ~= 'function' then
					error("Bad entry in Create body: Key `[Create.E\'"..k.__eventname.."\']` must have a function value\
							got: "..tostring(v), 2)
				end
				obj[k.__eventname]:connect(v)


			--define constructor function
			elseif k == t.Create then
				if type(v) ~= 'function' then
					error("Bad entry in Create body: Key `[Create]` should be paired with a constructor function, \
							got: "..tostring(v), 2)
				elseif ctor then
					--ctor already exists, only one allowed
					error("Bad entry in Create body: Only one constructor function is allowed", 2)
				end
				ctor = v


			else
				error("Bad entry ("..tostring(k).." =&gt; "..tostring(v)..") in Create body", 2)
			end
		end

		--apply constructor function if it exists
		if ctor then
			ctor(obj)
		end

		if parent then
			obj.Parent = parent
		end

		--return the completed object
		return obj
	end
end

--now, create the functor:
Create = setmetatable({}, {__call = function(tb, ...) return Create_PrivImpl(...) end})

--and create the "Event.E" syntax stub. Really it's just a stub to construct a table which our Create
--function can recognize as special.
Create.E = function(eventName)
	return {__eventname = eventName}
end


Animations = {}

ServerControl = Tool:WaitForChild("ServerControl")
ClientControl = Tool:WaitForChild("ClientControl")

Rate = (1 / 60)

ToolEquipped = false

function SetAnimation(mode, value)
	if not ToolEquipped or not CheckIfAlive() then
		return
	end
	local function StopAnimation(Animation)
		for i, v in pairs(Animations) do
			if v.Animation == Animation then
				v.AnimationTrack:Stop(value.EndFadeTime)
				if v.TrackStopped then
					v.TrackStopped:disconnect()
				end
				table.remove(Animations, i)
			end
		end
	end
	if mode == "PlayAnimation" then
		for i, v in pairs(Animations) do
			if v.Animation == value.Animation then
				if value.Speed then
					v.AnimationTrack:AdjustSpeed(value.Speed)
					return
				elseif value.Weight or value.FadeTime then
					v.AnimationTrack:AdjustWeight(value.Weight, value.FadeTime)
					return
				else
					StopAnimation(value.Animation, false)
				end
			end
		end
		local AnimationMonitor = Create("Model"){}
		local TrackEnded = Create("StringValue"){Name = "Ended"}
		local AnimationTrack = Humanoid:LoadAnimation(value.Animation)
		local TrackStopped
		if not value.Manual then
			TrackStopped = AnimationTrack.Stopped:connect(function()
				if TrackStopped then
					TrackStopped:disconnect()
				end
				StopAnimation(value.Animation, true)
				TrackEnded.Parent = AnimationMonitor
			end)
		end
		table.insert(Animations, {Animation = value.Animation, AnimationTrack = AnimationTrack, TrackStopped = TrackStopped})
		AnimationTrack:Play(value.FadeTime, value.Weight, value.Speed)
		if TrackStopped then
			AnimationMonitor:WaitForChild(TrackEnded.Name)
		end
		return TrackEnded.Name
	elseif mode == "StopAnimation" and value then
		StopAnimation(value.Animation)
	end
end

function CheckIfAlive()
	return (((Character and Character.Parent and Humanoid and Humanoid.Parent and Humanoid.Health &gt; 0 and Player and Player.Parent) and true) or false)
end

function Equipped(Mouse)
	Character = Tool.Parent
	Player = Players:GetPlayerFromCharacter(Character)
	Humanoid = Character:FindFirstChild("Humanoid")
	ToolEquipped = true
	if not CheckIfAlive() then
		return
	end
	Spawn(function()
		PlayerMouse = Player:GetMouse()
		Mouse.Button1Down:connect(function()
			InvokeServer("Button1Click", {Down = true})
		end)
		Mouse.Button1Up:connect(function()
			InvokeServer("Button1Click", {Down = false})
		end)
		Mouse.KeyDown:connect(function(Key)
			InvokeServer("KeyPress", {Key = Key, Down = true})
		end)
		Mouse.KeyUp:connect(function(Key)
			InvokeServer("KeyPress", {Key = Key, Down = false})
		end)
		local PlayerGui = Player:FindFirstChild("PlayerGui")
		if PlayerGui then
			InputCheckClone = InputCheck:Clone()
			if UserInputService.TouchEnabled then
				InputCheckClone = InputCheck:Clone()
				InputCheckClone.InputButton.InputBegan:connect(function()
					InvokeServer("Button1Click", {Down = true})
				end)
				InputCheckClone.InputButton.InputEnded:connect(function()
					InvokeServer("Button1Click", {Down = false})
				end)
				InputCheckClone.Parent = PlayerGui
			end
		end
		for i, v in pairs(Tool:GetChildren()) do
			if v:IsA("Animation") then
				ContentProvider:Preload(v.AnimationId)
			end
		end
	end)
end

function Unequipped()
	if InputCheckClone then
		Debris:AddItem(InputCheckClone, 0)
	end
	for i, v in pairs(Animations) do
		if v and v.AnimationTrack then
			v.AnimationTrack:Stop()
		end
	end
	Animations = {}
	ToolEquipped = false
end

function InvokeServer(mode, value)
	local ServerReturn = nil
	pcall(function()
		ServerReturn = ServerControl:InvokeServer(mode, value)
	end)
	return ServerReturn
end

function OnClientInvoke(mode, value)
	if mode == "PlayAnimation" and value and ToolEquipped and Humanoid then
		SetAnimation("PlayAnimation", value)
	elseif mode == "StopAnimation" and value then
		SetAnimation("StopAnimation", value)
	elseif mode == "PlaySound" and value then
		value:Play()
	elseif mode == "StopSound" and value then
		value:Stop()
	elseif mode == "MousePosition" then
		return ((PlayerMouse and {Position = PlayerMouse.Hit.p, Target = PlayerMouse.Target}) or nil)
	end
end

ClientControl.OnClientInvoke = OnClientInvoke
Tool.Equipped:connect(Equipped)
Tool.Unequipped:connect(Unequipped)</ProtectedString>
						<int64 name="SourceAssetId">-1</int64>
						<BinaryString name="Tags" />
					</Properties>
				</Item>
				<Item class="LocalScript" referent="RBX209828BA0F4B4392A0F9361DC3B47233">
					<Properties>
						<BinaryString name="AttributesSerialize" />
						<SecurityCapabilities name="Capabilities">0</SecurityCapabilities>
						<bool name="DefinesCapabilities">false</bool>
						<bool name="Disabled">false</bool>
						<Content name="LinkedSource"><null /></Content>
						<string name="Name">MouseIcon</string>
						<token name="RunContext">0</token>
						<string name="ScriptGuid">{64C87A74-D4E3-4D2A-8E80-A66EF0501202}</string>
						<ProtectedString name="Source">Mouse_Icon = "rbxasset://textures/GunCursor.png"
Reloading_Icon = "rbxasset://textures/GunWaitCursor.png"

Tool = script.Parent

Mouse = nil

function UpdateIcon()
	if Mouse then
		Mouse.Icon = Tool.Enabled and Mouse_Icon or Reloading_Icon
	end
end

function OnEquipped(ToolMouse)
	Mouse = ToolMouse
	UpdateIcon()
end

Tool:GetPropertyChangedSignal("Enabled"):Connect(UpdateIcon)
Tool.Equipped:connect(OnEquipped)</ProtectedString>
						<int64 name="SourceAssetId">-1</int64>
						<BinaryString name="Tags" />
					</Properties>
				</Item>
				<Item class="Script" referent="RBX5AAFA6943B1B488DB3324FEEF307B1BF">
					<Properties>
						<BinaryString name="AttributesSerialize" />
						<SecurityCapabilities name="Capabilities">0</SecurityCapabilities>
						<bool name="DefinesCapabilities">false</bool>
						<bool name="Disabled">false</bool>
						<Content name="LinkedSource"><null /></Content>
						<string name="Name">Script</string>
						<token name="RunContext">0</token>
						<string name="ScriptGuid">{51532E59-56E1-46DF-9263-966DADA41092}</string>
						<ProtectedString name="Source">--Rescripted by Luckymaxer
--Updated for R15 avatars by StarWars

Tool = script.Parent
Handle = Tool:WaitForChild("Handle")
Mesh = Handle:WaitForChild("Mesh")

Players = game:GetService("Players")
Debris = game:GetService("Debris")

RbxUtility = LoadLibrary("RbxUtility")
Create = RbxUtility.Create

BaseUrl = "rbxassetid://"

Meshes = {
	GrappleWithHook = 2463972118,
	Grapple = 2463971088,
	Hook = 2463971527,
}

Animations = {
	Crouch = {Animation = Tool:WaitForChild("Crouch"), FadeTime = 0.25, Weight = nil, Speed = nil},
	R15Crouch = {Animation = Tool:WaitForChild("R15Crouch"), FadeTime = 0.25, Weight = nil, Speed = nil}
}

Sounds = {
	Fire = Handle:WaitForChild("Fire"),
	Connect = Handle:WaitForChild("Connect"),
	Hit = Handle:WaitForChild("Hit"),
}

for i, v in pairs(Meshes) do
	Meshes[i] = (BaseUrl .. v)
end

local BaseRopeConstraint = Instance.new("RopeConstraint")
BaseRopeConstraint.Thickness = 0.2
BaseRopeConstraint.Restitution = 1
BaseRopeConstraint.Color = BrickColor.new("Really black")

BasePart = Create("Part"){
	Material = Enum.Material.Plastic,
	Shape = Enum.PartType.Block,
	TopSurface = Enum.SurfaceType.Smooth,
	BottomSurface = Enum.SurfaceType.Smooth,
	Size = Vector3.new(0.2, 0.2, 0.2),
	CanCollide = true,
	Locked = true,
}

BaseRope = BasePart:Clone()
BaseRope.Name = "Effect"
BaseRope.BrickColor = BrickColor.new("Really black")
BaseRope.Anchored = true
BaseRope.CanCollide = false
Create("CylinderMesh"){
	Scale = Vector3.new(1, 1, 1),
	Parent = BaseRope,
}

BaseGrappleHook = BasePart:Clone()
BaseGrappleHook.Name = "Projectile"
BaseGrappleHook.Transparency = 0
BaseGrappleHook.Size = Vector3.new(1, 0.4, 1)
BaseGrappleHook.Anchored = false
BaseGrappleHook.CanCollide = true
Create("SpecialMesh"){
	MeshType = Enum.MeshType.FileMesh,
	MeshId = (BaseUrl .. "2463971527"),
	TextureId = (BaseUrl .. "2463972716"),
	Scale = Mesh.Scale,
	VertexColor = Vector3.new(1, 1, 1),
	Offset = Vector3.new(0, 0, 0),
	Parent = BaseGrappleHook,
}
local RopeAttachment = Instance.new("Attachment")
RopeAttachment.Name = "RopeAttachment"
RopeAttachment.Parent = BaseGrappleHook

Create("BodyGyro"){
	Parent = BaseGrappleHook,
}
for i, v in pairs({Sounds.Connect, Sounds.Hit}) do
	local Sound = v:Clone()
	Sound.Parent = BaseGrappleHook
end

Rate = (1 / 60)

MaxDistance = 200
CanFireWhileGrappling = true

Crouching = false
ToolEquipped = false

ServerControl = (Tool:FindFirstChild("ServerControl") or Create("RemoteFunction"){
	Name = "ServerControl",
	Parent = Tool,
})

ClientControl = (Tool:FindFirstChild("ClientControl") or Create("RemoteFunction"){
	Name = "ClientControl",
	Parent = Tool,
})

for i, v in pairs(Tool:GetChildren()) do
	if v:IsA("BasePart") and v ~= Handle then
		v:Destroy()
	end
end

Mesh.MeshId = Meshes.GrappleWithHook
Handle.Transparency = 0
Tool.Enabled = true

function CheckTableForString(Table, String)
	for i, v in pairs(Table) do
		if string.find(string.lower(String), string.lower(v)) then
			return true
		end
	end
	return false
end

function CheckIntangible(Hit)
	local ProjectileNames = {"Water", "Arrow", "Projectile", "Effect", "Rail", "Laser", "Bullet", "GrappleHook"}
	if Hit and Hit.Parent then
		if ((not Hit.CanCollide or CheckTableForString(ProjectileNames, Hit.Name)) and not Hit.Parent:FindFirstChild("Humanoid")) then
			return true
		end
	end
	return false
end

function CastRay(StartPos, Vec, Length, Ignore, DelayIfHit)
	local Ignore = ((type(Ignore) == "table" and Ignore) or {Ignore})
	local RayHit, RayPos, RayNormal = game:GetService("Workspace"):FindPartOnRayWithIgnoreList(Ray.new(StartPos, Vec * Length), Ignore)
	if RayHit and CheckIntangible(RayHit) then
		if DelayIfHit then
			wait()
		end
		RayHit, RayPos, RayNormal = CastRay((RayPos + (Vec * 0.01)), Vec, (Length - ((StartPos - RayPos).magnitude)), Ignore, DelayIfHit)
	end
	return RayHit, RayPos, RayNormal
end

function AdjustRope()
	if not Rope or not Rope.Parent or not CheckIfGrappleHookAlive() then
		return
	end
	local StartPosition = Handle.RopeAttachment.WorldPosition
	local EndPosition = GrappleHook.RopeAttachment.WorldPosition
	local RopeLength = (StartPosition - EndPosition).Magnitude

	Rope.Size = Vector3.new(1, 1, 1)
	Rope.Mesh.Scale = Vector3.new(0.1, RopeLength, 0.1)
	Rope.CFrame = (CFrame.new(((StartPosition + EndPosition) / 2), EndPosition) * CFrame.Angles(-(math.pi / 2), 0, 0))
end

function DisconnectGrappleHook(KeepBodyObjects)
	for i, v in pairs({Rope, GrappleHook, GrappleHookChanged}) do
		if v then
			if tostring(v) == "Connection" then
				v:disconnect()
			elseif type(v) == "userdata" and v.Parent then
				v:Destroy()
			end
		end
	end
	if CheckIfAlive() and not KeepBodyObjects then
		for i, v in pairs(Torso:GetChildren()) do
			if string.find(string.lower(v.ClassName), string.lower("Body")) then
				v:Destroy()
			end
		end
	end
	Connected = false
	Mesh.MeshId = Meshes.GrappleWithHook
end

function TryToConnect()
	if not ToolEquipped or not CheckIfAlive() or not CheckIfGrappleHookAlive() or Connected then
		DisconnectGrappleHook()
		return
	end
	local DistanceApart = (Torso.Position - GrappleHook.Position).Magnitude
	if DistanceApart &gt; MaxDistance then
		DisconnectGrappleHook()
		return
	end
	local Directions = {Vector3.new(0, 1, 0), Vector3.new(0, -1, 0), Vector3.new(1, 0, 0), Vector3.new(-1, 0, 0), Vector3.new(0, 0, 1), Vector3.new(0, 0, -1)}
	local ClosestRay = {DistanceApart = math.huge}
	for i, v in pairs(Directions) do
		local Direction = CFrame.new(GrappleHook.Position, (GrappleHook.CFrame + v * 2).p).lookVector
		local RayHit, RayPos, RayNormal = CastRay((GrappleHook.Position + Vector3.new(0, 0, 0)), Direction, 2, {Character, GrappleHook, Rope}, false)
		if RayHit then
			local DistanceApart = (GrappleHook.Position - RayPos).Magnitude
			if DistanceApart &lt; ClosestRay.DistanceApart then
				ClosestRay = {Hit = RayHit, Pos = RayPos, Normal = RayNormal, DistanceApart = DistanceApart}
			end
		end
	end
	if ClosestRay.Hit then
		Connected = true
		local GrappleCFrame = CFrame.new(ClosestRay.Pos, (CFrame.new(ClosestRay.Pos) + ClosestRay.Normal * 2).p) * CFrame.Angles((math.pi / 2), 0, 0)
		GrappleCFrame = (GrappleCFrame * CFrame.new(0, -(GrappleHook.Size.Y / 1.5), 0))
		GrappleCFrame = (CFrame.new(GrappleCFrame.p, Handle.Position) * CFrame.Angles(0, math.pi, 0))
		local Weld = Create("Motor6D"){
			Part0 = GrappleHook,
			Part1 = ClosestRay.Hit,
			C0 = GrappleCFrame:inverse(),
			C1 = ClosestRay.Hit.CFrame:inverse(),
			Parent = GrappleHook,
		}
		for i, v in pairs(GrappleHook:GetChildren()) do
			if string.find(string.lower(v.ClassName), string.lower("Body")) then
				v:Destroy()
			end
		end
		local HitSound = GrappleHook:FindFirstChild("Hit")
		if HitSound then
			HitSound:Play()
		end
		local BackUpGrappleHook = GrappleHook
		wait(0.4)
		if not CheckIfGrappleHookAlive() or GrappleHook ~= BackUpGrappleHook then
			return
		end
		Sounds.Connect:Play()
		local ConnectSound = GrappleHook:FindFirstChild("Connect")
		if ConnectSound then
			ConnectSound:Play()
		end

		for i, v in pairs(Torso:GetChildren()) do
			if string.find(string.lower(v.ClassName), string.lower("Body")) then
				v:Destroy()
			end
		end

		local TargetPosition = GrappleHook.Position
		local BackUpPosition = TargetPosition

		local BodyPos = Create("BodyPosition"){
			D = 1000,
			P = 3000,
			maxForce = Vector3.new(1000000, 1000000, 1000000),
			position = TargetPosition,
			Parent = Torso,
		}

		local BodyGyro = Create("BodyGyro"){
			maxTorque = Vector3.new(100000, 100000, 100000),
			cframe = CFrame.new(Torso.Position, Vector3.new(GrappleCFrame.p.X, Torso.Position.Y, GrappleCFrame.p.Z)),
			Parent = Torso,
		}

		Spawn(function()
			while TargetPosition == BackUpPosition and CheckIfGrappleHookAlive() and Connected and ToolEquipped and CheckIfAlive() do
				BodyPos.position = GrappleHook.Position
				wait()
			end
		end)

	end
end

function CheckIfGrappleHookAlive()
	return (((GrappleHook and GrappleHook.Parent --[[and Rope and Rope.Parent]]) and true) or false)
end

function CheckIfAlive()
	return (((Character and Character.Parent and Humanoid and Humanoid.Parent and Humanoid.Health &gt; 0 and Torso and Torso.Parent and Player and Player.Parent) and true) or false)
end

function Activated()
	if not Tool.Enabled or not ToolEquipped or not CheckIfAlive() then
		return
	end
	local MousePosition = InvokeClient("MousePosition")
	if not MousePosition then
		return
	end
	MousePosition = MousePosition.Position
	if CheckIfGrappleHookAlive() then
		if not CanFireWhileGrappling then
			return
		end
		if GrappleHookChanged then
			GrappleHookChanged:disconnect()
		end
		DisconnectGrappleHook(true)
	end
	if GrappleHookChanged then
		GrappleHookChanged:disconnect()
	end
	Tool.Enabled = false
	Sounds.Fire:Play()
	Mesh.MeshId = Meshes.Grapple
	GrappleHook = BaseGrappleHook:Clone()
	GrappleHook.CFrame = (CFrame.new((Handle.Position + (MousePosition - Handle.Position).Unit * 5), MousePosition) * CFrame.Angles(0, 0, 0))
	local Weight = 70
	GrappleHook.Velocity = (GrappleHook.CFrame.lookVector * Weight)
	local Force = Create("BodyForce"){
		force = Vector3.new(0, workspace.Gravity * 0.98 * GrappleHook:GetMass(), 0),
		Parent = GrappleHook,
	}
	GrappleHook.Parent = Tool
	GrappleHookChanged = GrappleHook.Changed:connect(function(Property)
		if Property == "Parent" then
			DisconnectGrappleHook()
		end
	end)
	Rope = BaseRope:Clone()
	Rope.Parent = Tool
	Spawn(function()
		while CheckIfGrappleHookAlive() and ToolEquipped and CheckIfAlive() do
			AdjustRope()
			Spawn(function()
				if not Connected then
					TryToConnect()
				end
			end)
			wait()
		end
	end)
	wait(2)
	Tool.Enabled = true
end

function Equipped(Mouse)
	Character = Tool.Parent
	Humanoid = Character:FindFirstChild("Humanoid")
	Torso = Character:FindFirstChild("Torso") or Character:FindFirstChild("UpperTorso")
	Player = Players:GetPlayerFromCharacter(Character)
	if not CheckIfAlive() then
		return
	end
	Spawn(function()
		DisconnectGrappleHook()
		if HumanoidJumping then
			HumanoidJumping:disconnect()
		end
		HumanoidJumping = Humanoid.Jumping:connect(function()
			DisconnectGrappleHook()
		end)
	end)
	Crouching = false
	ToolEquipped = true
end

function Unequipped()
	if HumanoidJumping then
		HumanoidJumping:disconnect()
	end
	DisconnectGrappleHook()
	Crouching = false
	ToolEquipped = false
end

function OnServerInvoke(player, mode, value)
	if player ~= Player or not ToolEquipped or not value or not CheckIfAlive() then
		return
	end
	if mode == "KeyPress" then
		local Key = value.Key
		local Down = value.Down
		if Key == "q" and Down then
			DisconnectGrappleHook()
		elseif Key == "c" and Down then
			Crouching = not Crouching
			Spawn(function()
				local Animation = Animations.Crouch
				if Humanoid and Humanoid.RigType == Enum.HumanoidRigType.R15 then
					Animation = Animations.R15Crouch
				end
				InvokeClient(((Crouching and "PlayAnimation") or "StopAnimation"), Animation)
			end)
		end
	end
end

function InvokeClient(Mode, Value)
	local ClientReturn = nil
	pcall(function()
		ClientReturn = ClientControl:InvokeClient(Player, Mode, Value)
	end)
	return ClientReturn
end

ServerControl.OnServerInvoke = OnServerInvoke

Tool.Activated:connect(Activated)
Tool.Equipped:connect(Equipped)
Tool.Unequipped:connect(Unequipped)</ProtectedString>
						<int64 name="SourceAssetId">-1</int64>
						<BinaryString name="Tags" />
					</Properties>
				</Item>
				<Item class="Animation" referent="RBX0872DB9C7EF140D5993158F8D9AFBE25">
					<Properties>
						<Content name="AnimationId"><url>http://www.roblox.com/asset/?id=287325678</url></Content>
						<BinaryString name="AttributesSerialize" />
						<SecurityCapabilities name="Capabilities">0</SecurityCapabilities>
						<bool name="DefinesCapabilities">false</bool>
						<string name="Name">Crouch</string>
						<int64 name="SourceAssetId">-1</int64>
						<BinaryString name="Tags" />
					</Properties>
				</Item>
				<Item class="Animation" referent="RBXE6E1038D26D740788EF90083D95BA37F">
					<Properties>
						<Content name="AnimationId"><url>rbxassetid://537260400</url></Content>
						<BinaryString name="AttributesSerialize" />
						<SecurityCapabilities name="Capabilities">0</SecurityCapabilities>
						<bool name="DefinesCapabilities">false</bool>
						<string name="Name">R15Crouch</string>
						<int64 name="SourceAssetId">-1</int64>
						<BinaryString name="Tags" />
					</Properties>
				</Item>
				<Item class="Keyframe" referent="RBX7DDA54FAD639441EBAB31A12C9365E08">
					<Properties>
						<BinaryString name="AttributesSerialize" />
						<SecurityCapabilities name="Capabilities">0</SecurityCapabilities>
						<bool name="DefinesCapabilities">false</bool>
						<string name="Name">ThumbnailPose</string>
						<int64 name="SourceAssetId">-1</int64>
						<BinaryString name="Tags" />
						<float name="Time">0</float>
					</Properties>
					<Item class="Pose" referent="RBX4C1700670D884B9A86A788F867F3E8D5">
						<Properties>
							<BinaryString name="AttributesSerialize" />
							<CoordinateFrame name="CFrame">
								<X>0</X>
								<Y>0</Y>
								<Z>0</Z>
								<R00>1</R00>
								<R01>0</R01>
								<R02>0</R02>
								<R10>0</R10>
								<R11>1</R11>
								<R12>0</R12>
								<R20>0</R20>
								<R21>0</R21>
								<R22>1</R22>
							</CoordinateFrame>
							<SecurityCapabilities name="Capabilities">0</SecurityCapabilities>
							<bool name="DefinesCapabilities">false</bool>
							<token name="EasingDirection">1</token>
							<token name="EasingStyle">0</token>
							<string name="Name">UpperTorso</string>
							<int64 name="SourceAssetId">-1</int64>
							<BinaryString name="Tags" />
							<float name="Weight">0</float>
						</Properties>
						<Item class="Pose" referent="RBXAF174FD6964B4816ABB2ABE7FA71BE95">
							<Properties>
								<BinaryString name="AttributesSerialize" />
								<CoordinateFrame name="CFrame">
									<X>0</X>
									<Y>-6.70552254e-08</Y>
									<Z>-5.96046448e-08</Z>
									<R00>1</R00>
									<R01>0</R01>
									<R02>0</R02>
									<R10>0</R10>
									<R11>0.173648193</R11>
									<R12>-0.98480773</R12>
									<R20>0</R20>
									<R21>0.98480773</R21>
									<R22>0.173648193</R22>
								</CoordinateFrame>
								<SecurityCapabilities name="Capabilities">0</SecurityCapabilities>
								<bool name="DefinesCapabilities">false</bool>
								<token name="EasingDirection">1</token>
								<token name="EasingStyle">0</token>
								<string name="Name">RightUpperArm</string>
								<int64 name="SourceAssetId">-1</int64>
								<BinaryString name="Tags" />
								<float name="Weight">1</float>
							</Properties>
							<Item class="Pose" referent="RBX2A8C2DE7E4C44CBC9C17E33DB9DEC8DA">
								<Properties>
									<BinaryString name="AttributesSerialize" />
									<CoordinateFrame name="CFrame">
										<X>0</X>
										<Y>-1.49011612e-08</Y>
										<Z>3.7252903e-09</Z>
										<R00>1</R00>
										<R01>0</R01>
										<R02>0</R02>
										<R10>0</R10>
										<R11>0.98480773</R11>
										<R12>-0.173648179</R12>
										<R20>0</R20>
										<R21>0.173648179</R21>
										<R22>0.98480773</R22>
									</CoordinateFrame>
									<SecurityCapabilities name="Capabilities">0</SecurityCapabilities>
									<bool name="DefinesCapabilities">false</bool>
									<token name="EasingDirection">1</token>
									<token name="EasingStyle">0</token>
									<string name="Name">RightLowerArm</string>
									<int64 name="SourceAssetId">-1</int64>
									<BinaryString name="Tags" />
									<float name="Weight">1</float>
								</Properties>
								<Item class="Pose" referent="RBXB8E95B476A0C47DF8C6ED5094FB40DC0">
									<Properties>
										<BinaryString name="AttributesSerialize" />
										<CoordinateFrame name="CFrame">
											<X>0</X>
											<Y>0</Y>
											<Z>0</Z>
											<R00>1</R00>
											<R01>0</R01>
											<R02>0</R02>
											<R10>0</R10>
											<R11>1</R11>
											<R12>0</R12>
											<R20>0</R20>
											<R21>0</R21>
											<R22>1</R22>
										</CoordinateFrame>
										<SecurityCapabilities name="Capabilities">0</SecurityCapabilities>
										<bool name="DefinesCapabilities">false</bool>
										<token name="EasingDirection">1</token>
										<token name="EasingStyle">0</token>
										<string name="Name">RightHand</string>
										<int64 name="SourceAssetId">-1</int64>
										<BinaryString name="Tags" />
										<float name="Weight">1</float>
									</Properties>
								</Item>
							</Item>
						</Item>
					</Item>
				</Item>
				<Item class="Camera" referent="RBX337F2A770C3841BBB70D5F26FA4BA440">
					<Properties>
						<BinaryString name="AttributesSerialize" />
						<CoordinateFrame name="CFrame">
							<X>-2.65866828</X>
							<Y>2.12402701</Y>
							<Z>2.53697371</Z>
							<R00>0.637424886</R00>
							<R01>0.272355497</R01>
							<R02>-0.720771849</R02>
							<R10>-0</R10>
							<R11>0.935444713</R11>
							<R12>0.353473186</R12>
							<R20>0.770512462</R20>
							<R21>-0.225312606</R21>
							<R22>0.596275747</R22>
						</CoordinateFrame>
						<Ref name="CameraSubject">null</Ref>
						<token name="CameraType">0</token>
						<SecurityCapabilities name="Capabilities">0</SecurityCapabilities>
						<bool name="DefinesCapabilities">false</bool>
						<float name="FieldOfView">70</float>
						<token name="FieldOfViewMode">0</token>
						<CoordinateFrame name="Focus">
							<X>-1.21712458</X>
							<Y>1.41708064</Y>
							<Z>1.34442222</Z>
							<R00>1</R00>
							<R01>0</R01>
							<R02>0</R02>
							<R10>0</R10>
							<R11>1</R11>
							<R12>0</R12>
							<R20>0</R20>
							<R21>0</R21>
							<R22>1</R22>
						</CoordinateFrame>
						<bool name="HeadLocked">true</bool>
						<float name="HeadScale">1</float>
						<string name="Name">ThumbnailCamera</string>
						<int64 name="SourceAssetId">-1</int64>
						<BinaryString name="Tags" />
						<bool name="VRTiltAndRollEnabled">false</bool>
					</Properties>
				</Item>
			</Item>
		</Item>
		